auxipackage_b1/__init__.py
auxipackage_b1/mathfunc.py
auxipackage_b1-0.0.1.dist-info/METADATA
auxipackage_b1-0.0.1.dist-info/WHEEL
auxipackage_b1-0.0.1.dist-info/top_level.txt
auxipackage_b1-0.0.1.dist-info/RECORD
