Metadata-Version: 2.1
Name: auxipackage-b1
Version: 0.0.1
Summary: My package to help me.
Author: xalw3r
Classifier: Programming Language :: Python :: 3
Classifier: License :: OSI Approved :: MIT License
Classifier: Operating System :: OS Independent
Requires-Python: >=3.7
